TensorflowJiqiXuexiMijiZhongwenDierBanChuyi/README.md
TensorflowJiqiXuexiMijiZhongwenDierBanChuyi/__init__.py
TensorflowJiqiXuexiMijiZhongwenDierBanChuyi/__main__.py
TensorflowJiqiXuexiMijiZhongwenDierBanChuyi/file.epub
TensorflowJiqiXuexiMijiZhongwenDierBanChuyi/index.html
TensorflowJiqiXuexiMijiZhongwenDierBanChuyi/css/__init__.py
TensorflowJiqiXuexiMijiZhongwenDierBanChuyi/css/annotations.css
TensorflowJiqiXuexiMijiZhongwenDierBanChuyi/css/main.css
TensorflowJiqiXuexiMijiZhongwenDierBanChuyi/css/normalize.css
TensorflowJiqiXuexiMijiZhongwenDierBanChuyi/css/popup.css
TensorflowJiqiXuexiMijiZhongwenDierBanChuyi/font/__init__.py
TensorflowJiqiXuexiMijiZhongwenDierBanChuyi/font/fontello.eot
TensorflowJiqiXuexiMijiZhongwenDierBanChuyi/font/fontello.svg
TensorflowJiqiXuexiMijiZhongwenDierBanChuyi/font/fontello.ttf
TensorflowJiqiXuexiMijiZhongwenDierBanChuyi/font/fontello.woff
TensorflowJiqiXuexiMijiZhongwenDierBanChuyi/img/__init__.py
TensorflowJiqiXuexiMijiZhongwenDierBanChuyi/img/annotator-glyph-sprite.png
TensorflowJiqiXuexiMijiZhongwenDierBanChuyi/img/annotator-icon-sprite.png
TensorflowJiqiXuexiMijiZhongwenDierBanChuyi/img/apple-touch-icon.png
TensorflowJiqiXuexiMijiZhongwenDierBanChuyi/img/cancelfullscreen.png
TensorflowJiqiXuexiMijiZhongwenDierBanChuyi/img/close.png
TensorflowJiqiXuexiMijiZhongwenDierBanChuyi/img/fullscreen.png
TensorflowJiqiXuexiMijiZhongwenDierBanChuyi/img/loader.gif
TensorflowJiqiXuexiMijiZhongwenDierBanChuyi/img/menu-icon.png
TensorflowJiqiXuexiMijiZhongwenDierBanChuyi/img/save.png
TensorflowJiqiXuexiMijiZhongwenDierBanChuyi/img/saved.png
TensorflowJiqiXuexiMijiZhongwenDierBanChuyi/img/settings-s.png
TensorflowJiqiXuexiMijiZhongwenDierBanChuyi/img/settings.png
TensorflowJiqiXuexiMijiZhongwenDierBanChuyi/img/star.png
TensorflowJiqiXuexiMijiZhongwenDierBanChuyi/js/__init__.py
TensorflowJiqiXuexiMijiZhongwenDierBanChuyi/js/epub.js
TensorflowJiqiXuexiMijiZhongwenDierBanChuyi/js/epub.min.js
tensorflow_jiqi_xuexi_miji_zhongwen_dier_ban_chuyi-2024.3.5.0.dist-info/METADATA
tensorflow_jiqi_xuexi_miji_zhongwen_dier_ban_chuyi-2024.3.5.0.dist-info/WHEEL
tensorflow_jiqi_xuexi_miji_zhongwen_dier_ban_chuyi-2024.3.5.0.dist-info/entry_points.txt
tensorflow_jiqi_xuexi_miji_zhongwen_dier_ban_chuyi-2024.3.5.0.dist-info/top_level.txt
tensorflow_jiqi_xuexi_miji_zhongwen_dier_ban_chuyi-2024.3.5.0.dist-info/RECORD
